google/cloud/trace/__init__.py
google/cloud/trace/gapic_version.py
google/cloud/trace/py.typed
google/cloud/trace_v1/__init__.py
google/cloud/trace_v1/gapic_metadata.json
google/cloud/trace_v1/gapic_version.py
google/cloud/trace_v1/py.typed
google/cloud/trace_v1/services/__init__.py
google/cloud/trace_v1/services/trace_service/__init__.py
google/cloud/trace_v1/services/trace_service/async_client.py
google/cloud/trace_v1/services/trace_service/client.py
google/cloud/trace_v1/services/trace_service/pagers.py
google/cloud/trace_v1/services/trace_service/transports/__init__.py
google/cloud/trace_v1/services/trace_service/transports/base.py
google/cloud/trace_v1/services/trace_service/transports/grpc.py
google/cloud/trace_v1/services/trace_service/transports/grpc_asyncio.py
google/cloud/trace_v1/services/trace_service/transports/rest.py
google/cloud/trace_v1/services/trace_service/transports/rest_base.py
google/cloud/trace_v1/types/__init__.py
google/cloud/trace_v1/types/trace.py
google/cloud/trace_v2/__init__.py
google/cloud/trace_v2/gapic_metadata.json
google/cloud/trace_v2/gapic_version.py
google/cloud/trace_v2/py.typed
google/cloud/trace_v2/services/__init__.py
google/cloud/trace_v2/services/trace_service/__init__.py
google/cloud/trace_v2/services/trace_service/async_client.py
google/cloud/trace_v2/services/trace_service/client.py
google/cloud/trace_v2/services/trace_service/transports/__init__.py
google/cloud/trace_v2/services/trace_service/transports/base.py
google/cloud/trace_v2/services/trace_service/transports/grpc.py
google/cloud/trace_v2/services/trace_service/transports/grpc_asyncio.py
google/cloud/trace_v2/services/trace_service/transports/rest.py
google/cloud/trace_v2/services/trace_service/transports/rest_base.py
google/cloud/trace_v2/types/__init__.py
google/cloud/trace_v2/types/trace.py
google/cloud/trace_v2/types/tracing.py
google_cloud_trace-1.16.1.dist-info/LICENSE
google_cloud_trace-1.16.1.dist-info/METADATA
google_cloud_trace-1.16.1.dist-info/WHEEL
google_cloud_trace-1.16.1.dist-info/top_level.txt
google_cloud_trace-1.16.1.dist-info/RECORD
